[
  {
    "time": "10:00",
    "med": "AM",
    "event": "Wedding Ceremony",
    "icon": "rings"
  },
  {
    "time": "11:00",
    "med": "AM",
    "event": "Wedding Photographs",
    "icon": "camera"
  },
  {
    "time": "11:30",
    "med": "AM",
    "event": "Reception",
    "icon": "reception"
  },
  {
    "time": "12:00",
    "med": "NN",
    "event": "Lunch is served",
    "icon": "utensils"
  },
  {
    "time": "1:00",
    "med": "PM",
    "event": "Wedding Reception Program",
    "icon": "celebration"
  }
]
